find_old_large_files/__init__.py
find_old_large_files/find_old_large_files.py
find_old_large_files-0.4.6.dist-info/LICENSE
find_old_large_files-0.4.6.dist-info/METADATA
find_old_large_files-0.4.6.dist-info/WHEEL
find_old_large_files-0.4.6.dist-info/entry_points.txt
find_old_large_files-0.4.6.dist-info/top_level.txt
find_old_large_files-0.4.6.dist-info/RECORD
