Metadata-Version: 2.1
Name: find-old-large-files
Version: 0.4.6
Summary: A utility to find and remove large, old files.
Home-page: http://github.com/PrinceDisant/find_old_large_files
Author: Disant Upadhyay
Author-email: disantupadhyay07@gmail.com
License-File: LICENSE
Requires-Dist: tqdm
